garpix_order/MANIFEST.in
garpix_order/README.rst
garpix_order/__init__.py
garpix_order/apps.py
garpix_order/exceptions.py
garpix_order/pyproject.toml
garpix_order/setup.py
garpix_order/tests.py
garpix_order/urls.py
garpix_order/utils.py
garpix_order/__pycache__/__init__.cpython-311.pyc
garpix_order/__pycache__/__init__.cpython-38.pyc
garpix_order/__pycache__/apps.cpython-311.pyc
garpix_order/__pycache__/apps.cpython-38.pyc
garpix_order/__pycache__/urls.cpython-311.pyc
garpix_order/__pycache__/urls.cpython-38.pyc
garpix_order/__pycache__/utils.cpython-311.pyc
garpix_order/__pycache__/utils.cpython-38.pyc
garpix_order/admin/__init__.py
garpix_order/admin/home_page.py
garpix_order/admin/recurring.py
garpix_order/admin/__pycache__/__init__.cpython-311.pyc
garpix_order/admin/__pycache__/__init__.cpython-38.pyc
garpix_order/logging/__init__.py
garpix_order/logging/filters/__init__.py
garpix_order/logging/filters/payment_auth_data_filter.py
garpix_order/migrations/0001_initial.py
garpix_order/migrations/0002_auto_20230703_1624.py
garpix_order/migrations/0003_robokassainvoice.py
garpix_order/migrations/__init__.py
garpix_order/models/__init__.py
garpix_order/models/config.py
garpix_order/models/order.py
garpix_order/models/order_item.py
garpix_order/models/payment.py
garpix_order/models/__pycache__/__init__.cpython-311.pyc
garpix_order/models/__pycache__/__init__.cpython-38.pyc
garpix_order/models/__pycache__/config.cpython-311.pyc
garpix_order/models/__pycache__/config.cpython-38.pyc
garpix_order/models/__pycache__/order.cpython-311.pyc
garpix_order/models/__pycache__/order.cpython-38.pyc
garpix_order/models/__pycache__/order_item.cpython-311.pyc
garpix_order/models/__pycache__/order_item.cpython-38.pyc
garpix_order/models/__pycache__/payment.cpython-311.pyc
garpix_order/models/__pycache__/payment.cpython-38.pyc
garpix_order/models/payments/__init__.py
garpix_order/models/payments/bank_card.py
garpix_order/models/payments/cash.py
garpix_order-1.0.0rc9.dist-info/METADATA
garpix_order-1.0.0rc9.dist-info/WHEEL
garpix_order-1.0.0rc9.dist-info/top_level.txt
garpix_order-1.0.0rc9.dist-info/RECORD
